LICENSE
MANIFEST.in
README.md
setup.py
pycanvas/__init__.py
pycanvas.egg-info/PKG-INFO
pycanvas.egg-info/SOURCES.txt
pycanvas.egg-info/dependency_links.txt
pycanvas.egg-info/requires.txt
pycanvas.egg-info/top_level.txt
pycanvas/apis/__init__.py
pycanvas/apis/account_domain_lookups.py
pycanvas/apis/account_notifications.py
pycanvas/apis/account_reports.py
pycanvas/apis/accounts.py
pycanvas/apis/admins.py
pycanvas/apis/announcement_external_feeds.py
pycanvas/apis/appointment_groups.py
pycanvas/apis/assignment_groups.py
pycanvas/apis/assignments.py
pycanvas/apis/authentications_log.py
pycanvas/apis/base.py
pycanvas/apis/calendar_events.py
pycanvas/apis/collaborations.py
pycanvas/apis/comm_messages.py
pycanvas/apis/communication_channels.py
pycanvas/apis/conferences.py
pycanvas/apis/content_exports.py
pycanvas/apis/content_migrations.py
pycanvas/apis/conversations.py
pycanvas/apis/course_audit_log.py
pycanvas/apis/course_quiz_extensions.py
pycanvas/apis/courses.py
pycanvas/apis/custom_gradebook_columns.py
pycanvas/apis/discussion_topics.py
pycanvas/apis/document_previews.py
pycanvas/apis/enrollment_terms.py
pycanvas/apis/enrollments.py
pycanvas/apis/external_tools.py
pycanvas/apis/favorites.py
pycanvas/apis/feature_flags.py
pycanvas/apis/files.py
pycanvas/apis/grade_change_log.py
pycanvas/apis/gradebook_history.py
pycanvas/apis/grading_periods.py
pycanvas/apis/grading_standards.py
pycanvas/apis/group_categories.py
pycanvas/apis/groups.py
pycanvas/apis/live_assessments.py
pycanvas/apis/logins.py
pycanvas/apis/modules.py
pycanvas/apis/notification_preferences.py
pycanvas/apis/outcome_groups.py
pycanvas/apis/outcome_results.py
pycanvas/apis/outcomes.py
pycanvas/apis/pages.py
pycanvas/apis/poll_choices.py
pycanvas/apis/poll_sessions.py
pycanvas/apis/poll_submissions.py
pycanvas/apis/polls.py
pycanvas/apis/progress.py
pycanvas/apis/quiz_assignment_overrides.py
pycanvas/apis/quiz_extensions.py
pycanvas/apis/quiz_ip_filters.py
pycanvas/apis/quiz_question_groups.py
pycanvas/apis/quiz_questions.py
pycanvas/apis/quiz_reports.py
pycanvas/apis/quiz_statistics.py
pycanvas/apis/quiz_submission_events.py
