Metadata-Version: 1.1
Name: pycanvas
Version: 0.2.4
Summary: Client library for the Instructure Canvas REST api.
Home-page: https://github.com/PGower/PyCanvas
Author: Paul Gower
Author-email: p.gower@gmail.com
License: BSD
Download-URL: https://github.com/PGower/PyCanvas/releases
Keywords: canvas,instructure
Platform: UNKNOWN
Classifier: Development Status :: 3 - Alpha
Classifier: Environment :: Web Environment
Classifier: Programming Language :: Python
Classifier: Intended Audience :: Developers
Classifier: License :: OSI Approved :: MIT License
Classifier: Operating System :: OS Independent
Classifier: Topic :: Software Development :: Libraries :: Python Modules
